pecos/__init__.py
pecos/graphics.py
pecos/io.py
pecos/logger.py
pecos/metrics.py
pecos/monitoring.py
pecos/pv.py
pecos/utils.py
pecos/templates/base.html
pecos/templates/dashboard.html
pecos/templates/device_to_client.yml
pecos/templates/monitoring_report.html
pecos/templates/monitoring_report.tex
pecos/tests/data/Simple_test_results.csv
pecos/tests/data/Simple_test_results_with_timezone.csv
pecos/tests/data/TEST_config.yml
pecos/tests/data/TEST_db1_2014_01_01.dat
pecos/tests/data/delta_summary_100.csv
pecos-1.0.0.dist-info/LICENSE.txt
pecos-1.0.0.dist-info/METADATA
pecos-1.0.0.dist-info/WHEEL
pecos-1.0.0.dist-info/top_level.txt
pecos-1.0.0.dist-info/RECORD
