Metadata-Version: 2.2
Name: pecos
Version: 1.0.0
Summary: Python package for performance monitoring of time series data.
Home-page: https://github.com/sandialabs/pecos
Author: Pecos Developers
Maintainer-email: kaklise@sandia.gov
License: Revised BSD
License-File: LICENSE.txt
Requires-Dist: numpy>=1.10.4
Requires-Dist: pandas>=0.18.0
Requires-Dist: matplotlib
Requires-Dist: jinja2
Requires-Dist: pytest
Dynamic: author
Dynamic: description
Dynamic: home-page
Dynamic: license
Dynamic: maintainer-email
Dynamic: requires-dist
Dynamic: summary
